get_nhanes/__init__.py
get_nhanes/config.py
get_nhanes/coreCalculated/AIPCalculated.py
get_nhanes/coreCalculated/BMICalculated.py
get_nhanes/coreCalculated/BRICalculated.py
get_nhanes/coreCalculated/CKMCalculated.py
get_nhanes/coreCalculated/CVD10Calculated.py
get_nhanes/coreCalculated/FIB4Calculated.py
get_nhanes/coreCalculated/HALPCalculated.py
get_nhanes/coreCalculated/HRRCalculated.py
get_nhanes/coreCalculated/MARCalculated.py
get_nhanes/coreCalculated/NLRCalculated.py
get_nhanes/coreCalculated/NPARCalculated.py
get_nhanes/coreCalculated/RARCalculated.py
get_nhanes/coreCalculated/SBPCalculated.py
get_nhanes/coreCalculated/SIICalculated.py
get_nhanes/coreCalculated/TyGCalculated.py
get_nhanes/coreCalculated/TyG_BMI.py
get_nhanes/coreCalculated/UHRCalculated.py
get_nhanes/coreCalculated/VAICalculated.py
get_nhanes/coreCalculated/__init__.py
get_nhanes/coreCalculated/eGFRCalculated.py
get_nhanes/coreCalculated/phenoAgeCalculated.py
get_nhanes/getCovariates/__init__.py
get_nhanes/getCovariates/covariates.py
get_nhanes/getCovariates/weightAll.py
get_nhanes/getMortality/MortalityData.py
get_nhanes/getMortality/__init__.py
get_nhanes/utils/__init__.py
get_nhanes/utils/getMetricsConvenient.py
get_nhanes/utils/racialReconstruction.py
get_nhanes-0.1.2.dist-info/licenses/LICENSE
get_nhanes-0.1.2.dist-info/METADATA
get_nhanes-0.1.2.dist-info/WHEEL
get_nhanes-0.1.2.dist-info/top_level.txt
get_nhanes-0.1.2.dist-info/RECORD
