Metadata-Version: 2.4
Name: get_nhanes
Version: 0.1.2
Summary: A Python package for processing NHANES data
Home-page: https://github.com/wqlttt/getNhanes
Author: wqlt
Author-email: P2415627@mpu.edu.mo
Classifier: Programming Language :: Python :: 3
Classifier: License :: OSI Approved :: MIT License
Classifier: Operating System :: OS Independent
Requires-Python: >=3.6
License-File: LICENSE
Requires-Dist: pandas
Requires-Dist: numpy
Dynamic: author
Dynamic: author-email
Dynamic: classifier
Dynamic: description
Dynamic: description-content-type
Dynamic: home-page
Dynamic: license-file
Dynamic: requires-dist
Dynamic: requires-python
Dynamic: summary
